{"xKore": ["http://www.sputnikmusic.com/images/bands/33074.jpg", ["Electronic"], "None", {"Full Russian": [0, "http://www.sputnikmusic.com/images/albums/92283.jpg"], "Lazershark": [0, "http://www.sputnikmusic.com/images/albums/109011.jpg"], "The Domination": [0, "http://www.sputnikmusic.com/images/albums/109012.jpg"], "Stabs": [0, "http://www.sputnikmusic.com/images/albums/109010.jpg"]}], "XPUS": ["http://www.sputnikmusic.com/images/bands/73602.jpg", ["Death Metal", "Black Metal"], "None", {"Sanctus Dominus Deus Sabaoth": [0, "http://www.sputnikmusic.com/images/albums/210257.jpg"]}], "XIV Dark Centuries": ["http://www.sputnikmusic.com/images/unknown2.jpg", [], "None", {}], "XTC (jungle)": ["http://www.sputnikmusic.com/images/unknown2.jpg", [], "None", {"XTC EP": [0, "http://www.sputnikmusic.com/images/albums/233743.jpg"]}], "Xiu Xiu": ["http://www.sputnikmusic.com/images/bands/2600.jpg", ["Experimental", "Post Punk", "Electronic"], "None", {"Dear God, I Hate Myself": [0, "http://www.sputnikmusic.com/images/albums/47596.jpg"], "Tu Mi Piaci EP": [0, "http://www.sputnikmusic.com/images/albums/15424.jpg"], "House Plant Music": [0, "http://www.sputnikmusic.com/images/albums/220931.jpg"], "Daphny": [0, "http://www.sputnikmusic.com/images/albums/178453.jpg"], "Kling Klang": [0, "http://www.sputnikmusic.com/images/albums/208276.jpg"], "Australia-New Zealand Tour EP": [0, "http://www.sputnikmusic.com/images/albums/188645.jpg"], "Always": [0, "http://www.sputnikmusic.com/images/albums/92515.jpg"], "A Promise": [0, "http://www.sputnikmusic.com/images/albums/6261.jpg"], "Respectful & Clean": [0, "http://www.sputnikmusic.com/images/albums/198189.jpg"], "The Air Force": [0, "http://www.sputnikmusic.com/images/albums/14929.jpg"], "Nina": [0, "http://www.sputnikmusic.com/images/albums/141676.jpg"], "Chapel of the Chimes": [0, "http://www.sputnikmusic.com/images/albums/122376.jpg"], "Fabulous Muscles": [0, "http://www.sputnikmusic.com/images/albums/9663.jpg"], "Women As Lovers": [0, "http://www.sputnikmusic.com/images/albums/23563.jpg"], "Fag Patrol": [0, "http://www.sputnikmusic.com/images/albums/57545.jpg"], "Plays The Music Of Twin Peaks": [0, "http://www.sputnikmusic.com/images/albums/218052.jpg"], "Angel Guts: Red Classroom": [0, "http://www.sputnikmusic.com/images/albums/146702.jpg"], "La Foret": [0, "http://www.sputnikmusic.com/images/albums/8488.jpg"], "Knife Play": [0, "http://www.sputnikmusic.com/images/albums/17133.jpg"], "Unclouded Sky": [0, "http://www.sputnikmusic.com/images/albums/159668.jpg"], "There Is No Right, There Is No Wrong": [0, "http://www.sputnikmusic.com/images/albums/188646.jpg"]}], "XXXTENTACION": ["http://www.sputnikmusic.com/images/unknown2.jpg", ["Hip-Hop"], "None", {"Bad Vibes Forever": [0, "http://www.sputnikmusic.com/images/albums/232696.jpg"]}], "X Ray Cat Trio": ["http://www.sputnikmusic.com/images/unknown2.jpg", ["Rock"], "None", {"Bloody Deeds": [0, "http://www.sputnikmusic.com/images/albums/214921.jpg"], "Out For Blood": [0, "http://www.sputnikmusic.com/images/albums/214920.jpg"]}], "Xavier Rudd": ["http://www.sputnikmusic.com/images/bands/601.jpg", ["Folk"], "None", {"To Let": [0, "http://www.sputnikmusic.com/images/albums/985.jpg"], "Solace": [0, "http://www.sputnikmusic.com/images/albums/17528.jpg"], "White Moth": [0, "http://www.sputnikmusic.com/images/albums/18370.jpg"], "Food In The Belly": [0, "http://www.sputnikmusic.com/images/albums/16930.jpg"], "Dark Shades of Blue": [0, "http://www.sputnikmusic.com/images/albums/30265.jpg"], "Koonyum Sun": [0, "http://www.sputnikmusic.com/images/albums/64973.jpg"], "Good Spirit": [0, "http://www.sputnikmusic.com/images/albums/18453.jpg"], "Live At The Grid": [0, "http://www.sputnikmusic.com/images/albums/18600.jpg"], "Spirit Bird": [0, "http://www.sputnikmusic.com/images/albums/103420.jpg"]}], "Xibalba": ["http://www.sputnikmusic.com/images/bands/27385.jpg", ["Hardcore", "Sludge Metal", "Death Metal"], "None", {"Hasta La Muerte": [0, "http://www.sputnikmusic.com/images/albums/107214.jpg"], "Tierra Y Libertad": [0, "http://www.sputnikmusic.com/images/albums/177463.jpg"], "Madre Mia Gracias Por Los Dias": [0, "http://www.sputnikmusic.com/images/albums/76718.jpg"]}], "Xudef Klas": ["http://www.sputnikmusic.com/images/bands/41419.jpg", ["Thrash Metal"], "None", {"Eutanasia": [0, "http://www.sputnikmusic.com/images/albums/114947.jpg"], "Igual De Claro": [0, "http://www.sputnikmusic.com/images/albums/114946.jpg"]}], "Xterminators": ["http://www.sputnikmusic.com/images/unknown2.jpg", [], "None", {"Microwave Radiation": [0, "http://www.sputnikmusic.com/images/albums/155891.jpg"]}], "Xoth": ["http://www.sputnikmusic.com/images/bands/60223.jpg", ["Death Metal", "Black Metal", "Heavy Metal"], "None", {"Hostile Terraforming": [0, "http://www.sputnikmusic.com/images/albums/170652.jpg"]}], "X Suns": ["http://www.sputnikmusic.com/images/unknown2.jpg", ["Post Rock"], "None", {}], "Xbalanke": ["http://www.sputnikmusic.com/images/unknown2.jpg", ["Post Rock", "Jazz"], "None", {"Iridio": [0, "http://www.sputnikmusic.com/images/albums/89300.jpg"]}], "Xavier Rudd and Izintaba": ["http://www.sputnikmusic.com/images/unknown2.jpg", ["Folk"], "None", {"Koonyum Sun": [0, "http://www.sputnikmusic.com/images/albums/63823.jpg"]}], "Xurs": ["http://www.sputnikmusic.com/images/unknown2.jpg", [], "None", {"Xurs": [0, "http://www.sputnikmusic.com/images/albums/229787.jpg"]}], "Xabec": ["http://www.sputnikmusic.com/images/bands/67200.jpg", ["Ambient", "Drone", "Electronic"], "None", {"Feuerstern": [0, "http://www.sputnikmusic.com/images/albums/191722.jpg"]}], "Xerox": ["http://www.sputnikmusic.com/images/unknown2.jpg", ["Electronic"], "None", {"Frequency Drive": [0, "http://www.sputnikmusic.com/images/albums/126323.jpg"]}], "Xorcize": ["http://www.sputnikmusic.com/images/bands/59806.jpg", ["Thrash Metal", "Heavy Metal"], "None", {"Thoughts Filled With Fire": [0, "http://www.sputnikmusic.com/images/albums/169365.jpg"]}], "Xmal Deutschland": ["http://www.sputnikmusic.com/images/bands/5258.jpg", ["Post Punk", "Gothic"], "None", {"Viva": [0, "http://www.sputnikmusic.com/images/albums/15194.jpg"], "Tocsin": [0, "http://www.sputnikmusic.com/images/albums/15196.jpg"], "Fetisch": [0, "http://www.sputnikmusic.com/images/albums/15195.jpg"], "Devils": [0, "http://www.sputnikmusic.com/images/albums/15197.jpg"]}], "Xanthochroid": ["http://www.sputnikmusic.com/images/bands/41158.jpg", ["Black Metal", "Progressive Metal", "Folk"], "None", {"Blessed He With Boils": [0, "http://www.sputnikmusic.com/images/albums/114320.jpg"], "Incultus": [0, "http://www.sputnikmusic.com/images/albums/114238.jpg"]}], "Xehanort": ["http://www.sputnikmusic.com/images/unknown2.jpg", ["Death Metal", "Progressive Metal", "Metalcore"], "None", {"Secret Reports": [0, "http://www.sputnikmusic.com/images/albums/196264.jpg"], "Re:Birth": [0, "http://www.sputnikmusic.com/images/albums/220905.jpg"], "Birth": [0, "http://www.sputnikmusic.com/images/albums/101443.jpg"], "Awaken In A Different Dimension": [0, "http://www.sputnikmusic.com/images/albums/142305.jpg"]}], "Xerath": ["http://www.sputnikmusic.com/images/bands/13319.jpg", ["Death Metal", "Progressive Metal", "Classical"], "None", {"II": [0, "http://www.sputnikmusic.com/images/albums/74809.jpg"], "I": [0, "http://www.sputnikmusic.com/images/albums/37214.jpg"], "III": [0, "http://www.sputnikmusic.com/images/albums/166767.jpg"]}], "Xingu Hill": ["http://www.sputnikmusic.com/images/unknown2.jpg", ["Electronic", "IDM", "Ambient"], "None", {"Maps Of The Impossible": [0, "http://www.sputnikmusic.com/images/albums/231087.jpg"], "Alterity": [0, "http://www.sputnikmusic.com/images/albums/223713.jpg"]}], "Xiu Xiu Larsen": ["http://www.sputnikmusic.com/images/unknown2.jpg", ["Experimental"], "None", {"Ciautistico!": [0, "http://www.sputnikmusic.com/images/albums/200152.jpg"], "Dude": [0, "http://www.sputnikmusic.com/images/albums/200668.jpg"]}], "Xela & Jefre Cantu-Ledesma": ["http://www.sputnikmusic.com/images/unknown2.jpg", [], "None", {"Love is a Dream": [0, "http://www.sputnikmusic.com/images/albums/190915.jpg"]}], "X-Marks The Pedwalk": ["http://www.sputnikmusic.com/images/bands/18165.jpg", ["Industrial", "Techno"], "None", {"Air Back Trax": [0, "http://www.sputnikmusic.com/images/albums/53204.jpg"], "The Killing Had Begun": [0, "http://www.sputnikmusic.com/images/albums/49533.jpg"], "Facer": [0, "http://www.sputnikmusic.com/images/albums/227737.jpg"], "Meshwork": [0, "http://www.sputnikmusic.com/images/albums/49534.jpg"], "Abattoir": [0, "http://www.sputnikmusic.com/images/albums/208051.jpg"], "Four Fit (The Singles Collection Part II)": [0, "http://www.sputnikmusic.com/images/albums/53205.jpg"], "Human Desolation": [0, "http://www.sputnikmusic.com/images/albums/49532.jpg"], "Drawback": [0, "http://www.sputnikmusic.com/images/albums/49530.jpg"], "Experiences": [0, "http://www.sputnikmusic.com/images/albums/53207.jpg"], "Freaks": [0, "http://www.sputnikmusic.com/images/albums/49531.jpg"], "Cenotaph": [0, "http://www.sputnikmusic.com/images/albums/208052.jpg"], "Retrospective 88-99": [0, "http://www.sputnikmusic.com/images/albums/49529.jpg"], "Inner Zone Journey": [0, "http://www.sputnikmusic.com/images/albums/49528.jpg"], "Arbitrary Execution": [0, "http://www.sputnikmusic.com/images/albums/207762.jpg"]}], "X": ["http://www.sputnikmusic.com/images/bands/1551.jpg", ["Punk", "Alternative Rock", "Americana"], "None", {"Live At The Whiskey": [0, "http://www.sputnikmusic.com/images/albums/7457.jpg"], "The X Anthology": [0, "http://www.sputnikmusic.com/images/albums/14623.jpg"], "Ain't Love Grand": [0, "http://www.sputnikmusic.com/images/albums/7296.jpg"], "Live In Los Angeles": [0, "http://www.sputnikmusic.com/images/albums/3141.jpg"], "Hey Zeus": [0, "http://www.sputnikmusic.com/images/albums/9116.jpg"], "Unclogged": [0, "http://www.sputnikmusic.com/images/albums/8552.jpg"], "See How We Are": [0, "http://www.sputnikmusic.com/images/albums/8220.jpg"], "Los Angeles": [0, "http://www.sputnikmusic.com/images/albums/2967.jpg"], "Wild Gift": [0, "http://www.sputnikmusic.com/images/albums/3103.jpg"], "Under The Big Black Sun": [0, "http://www.sputnikmusic.com/images/albums/5196.jpg"], "More Fun In The New World": [0, "http://www.sputnikmusic.com/images/albums/8099.jpg"]}], "Xilent": ["http://www.sputnikmusic.com/images/unknown2.jpg", ["Dubstep", "Drum and Bass", "Electronic"], "None", {"Choose Me": [0, "http://www.sputnikmusic.com/images/albums/152005.jpg"]}], "X-Clan": ["http://www.sputnikmusic.com/images/bands/20684.jpg", ["Hip-Hop"], "None", {"Xodus - The New Testament": [0, "http://www.sputnikmusic.com/images/albums/58152.jpg"], "To The East, Blackwards": [0, "http://www.sputnikmusic.com/images/albums/58151.jpg"], "Return From Mecca": [0, "http://www.sputnikmusic.com/images/albums/58153.jpg"], "Mainstream Outlawz": [0, "http://www.sputnikmusic.com/images/albums/58154.jpg"]}], "Xasthur": ["http://www.sputnikmusic.com/images/bands/2362.jpg", ["Black Metal", "Ambient"], "None", {"Portal Of Sorrow": [0, "http://www.sputnikmusic.com/images/albums/52739.jpg"], "Telepathic With The Deceased": [0, "http://www.sputnikmusic.com/images/albums/26359.jpg"], "Xasthur": [0, "http://www.sputnikmusic.com/images/albums/232212.jpg"], "The Funeral of Being": [0, "http://www.sputnikmusic.com/images/albums/42731.jpg"], "Defective Epitaph": [0, "http://www.sputnikmusic.com/images/albums/21729.jpg"], "Suicide in Dark Serenity": [0, "http://www.sputnikmusic.com/images/albums/64807.jpg"], "All Reflections Drained": [0, "http://www.sputnikmusic.com/images/albums/37613.jpg"], "Nightmares at Dawn": [0, "http://www.sputnikmusic.com/images/albums/105447.jpg"], "Subject To Change": [0, "http://www.sputnikmusic.com/images/albums/232211.jpg"], "To Violate the Oblivious": [0, "http://www.sputnikmusic.com/images/albums/22302.jpg"], "Nocturnal Poisoning": [0, "http://www.sputnikmusic.com/images/albums/40946.jpg"], "A Gate Through Bloodstained Mirrors": [0, "http://www.sputnikmusic.com/images/albums/5532.jpg"], "A Darkened Winter": [0, "http://www.sputnikmusic.com/images/albums/86749.jpg"], "Subliminal Genocide": [0, "http://www.sputnikmusic.com/images/albums/15298.jpg"], "2005 Demo": [0, "http://www.sputnikmusic.com/images/albums/50258.jpg"]}], "X-box Murder": ["http://www.sputnikmusic.com/images/bands/56514.jpg", ["Death Metal", "Black Metal"], "None", {}], "XYZ": ["http://www.sputnikmusic.com/images/unknown2.jpg", [], "None", {"XYZ": [0, "http://www.sputnikmusic.com/images/albums/161090.jpg"]}], "Xipe Totec": ["http://www.sputnikmusic.com/images/unknown2.jpg", ["Death Metal"], "None", {"Rebirth into Essence": [0, "http://www.sputnikmusic.com/images/albums/51543.jpg"], "Rebirth Into Existence": [0, "http://www.sputnikmusic.com/images/albums/47456.jpg"]}], "xoxaineDEEZY": ["http://www.sputnikmusic.com/images/unknown2.jpg", [], "None", {"Almost Time": [0, "http://www.sputnikmusic.com/images/albums/201960.jpg"]}], "Xosar": ["http://www.sputnikmusic.com/images/bands/62572.jpg", ["House", "Techno"], "None", {"Holographic Matrix": [0, "http://www.sputnikmusic.com/images/albums/211643.jpg"], "Show Yourself": [0, "http://www.sputnikmusic.com/images/albums/213575.jpg"], "Tropical Cruize": [0, "http://www.sputnikmusic.com/images/albums/177716.jpg"], "Let Go": [0, "http://www.sputnikmusic.com/images/albums/190959.jpg"]}], "X-Raided": ["http://www.sputnikmusic.com/images/bands/11221.jpg", ["Hip-Hop"], "None", {"Deadly Game": [0, "http://www.sputnikmusic.com/images/albums/31899.jpg"], "And He Shall Appear": [0, "http://www.sputnikmusic.com/images/albums/31897.jpg"], "Psycho Active": [0, "http://www.sputnikmusic.com/images/albums/31869.jpg"], "X-Ology: The Best of X-Raided": [0, "http://www.sputnikmusic.com/images/albums/31895.jpg"], "Nefarious: Speak of Da Devil": [0, "http://www.sputnikmusic.com/images/albums/31906.jpg"], "City of Kings": [0, "http://www.sputnikmusic.com/images/albums/31901.jpg"], "These Walls Can Talk": [0, "http://www.sputnikmusic.com/images/albums/31898.jpg"], "Unforgiven": [0, "http://www.sputnikmusic.com/images/albums/31871.jpg"], "Ignition": [0, "http://www.sputnikmusic.com/images/albums/31900.jpg"], "Xorcist": [0, "http://www.sputnikmusic.com/images/albums/31870.jpg"], "Vengeance is Mine": [0, "http://www.sputnikmusic.com/images/albums/31894.jpg"], "The Initiation": [0, "http://www.sputnikmusic.com/images/albums/31896.jpg"]}], "Xalt": ["http://www.sputnikmusic.com/images/unknown2.jpg", ["Pop Rock"], "None", {"History": [0, "http://www.sputnikmusic.com/images/albums/98556.jpg"]}], "Xytras": ["http://www.sputnikmusic.com/images/bands/42755.jpg", [], "None", {"Passage": [0, "http://www.sputnikmusic.com/images/albums/118528.jpg"]}], "Xilentium": ["http://www.sputnikmusic.com/images/unknown2.jpg", ["Black Metal"], "None", {"Purity For All Aryans": [0, "http://www.sputnikmusic.com/images/albums/179143.jpg"]}], "XOV": ["http://www.sputnikmusic.com/images/bands/37181.jpg", ["Pop "], "None", {"Clowns": [0, "http://www.sputnikmusic.com/images/albums/103913.jpg"]}], "XXX Maniak": ["http://www.sputnikmusic.com/images/bands/3911.jpg", ["Grind"], "None", {"Harvesting The Cunt Nectar": [0, "http://www.sputnikmusic.com/images/albums/10540.jpg"]}], "Xenocide": ["http://www.sputnikmusic.com/images/bands/35129.jpg", ["Death Metal"], "None", {"Galactic Oppression": [0, "http://www.sputnikmusic.com/images/albums/98015.jpg"]}], "Xinlisupreme": ["http://www.sputnikmusic.com/images/bands/5656.jpg", ["Shoegaze", "Electronic", "Noise Rock"], "None", {"Tomorrow Never Comes": [0, "http://www.sputnikmusic.com/images/albums/16359.jpg"], "4 Bombs": [0, "http://www.sputnikmusic.com/images/albums/116944.jpg"], "Murder License": [0, "http://www.sputnikmusic.com/images/albums/212818.jpg"]}], "X-103": ["http://www.sputnikmusic.com/images/unknown2.jpg", ["Electronic", "Techno"], "None", {"Atlantis": [0, "http://www.sputnikmusic.com/images/albums/156310.jpg"], "Thera EP": [0, "http://www.sputnikmusic.com/images/albums/156309.jpg"]}], "Xanadu (UK)": ["http://www.sputnikmusic.com/images/bands/73824.jpg", ["Drum and Bass", "Electronic"], "None", {"Through The Oort Clouds": [0, "http://www.sputnikmusic.com/images/albums/210871.jpg"]}], "Xerxes (CH)": ["http://www.sputnikmusic.com/images/bands/78055.jpg", ["Progressive Rock"], "None", {"Beyond My Imagination": [0, "http://www.sputnikmusic.com/images/albums/222405.jpg"]}], "Xenohart": ["http://www.sputnikmusic.com/images/unknown2.jpg", [], "None", {"Birth": [0, "http://www.sputnikmusic.com/images/albums/142271.jpg"]}], "xanopticon": ["http://www.sputnikmusic.com/images/unknown2.jpg", ["Electronic", "IDM", "Breaks"], "None", {"Psicicite": [0, "http://www.sputnikmusic.com/images/albums/79385.jpg"], "Silver Key (EP)": [0, "http://www.sputnikmusic.com/images/albums/79383.jpg"], "Liminal Space": [0, "http://www.sputnikmusic.com/images/albums/79386.jpg"], "azif": [0, "http://www.sputnikmusic.com/images/albums/79384.jpg"]}], "xBishopx": ["http://www.sputnikmusic.com/images/bands/32965.jpg", ["Hardcore"], "None", {"Drugs": [0, "http://www.sputnikmusic.com/images/albums/92233.jpg"], "Suicide Party": [0, "http://www.sputnikmusic.com/images/albums/92023.jpg"]}], "Xiphiidae": ["http://www.sputnikmusic.com/images/bands/36526.jpg", ["Ambient", "Drone", "Experimental"], "None", {"Slowing Atrium": [0, "http://www.sputnikmusic.com/images/albums/130738.jpg"], "Sewn Within a Circle": [0, "http://www.sputnikmusic.com/images/albums/130723.jpg"], "Oval Lamb": [0, "http://www.sputnikmusic.com/images/albums/130733.jpg"], "Waning in Archaic Color Sequence": [0, "http://www.sputnikmusic.com/images/albums/130722.jpg"], "Quaking Myth": [0, "http://www.sputnikmusic.com/images/albums/130737.jpg"], "Interior Lamp with Leaves": [0, "http://www.sputnikmusic.com/images/albums/130732.jpg"], "Honeyguise": [0, "http://www.sputnikmusic.com/images/albums/130739.jpg"], "Honeyguide": [0, "http://www.sputnikmusic.com/images/albums/130714.jpg"], "Transresonance Formation": [0, "http://www.sputnikmusic.com/images/albums/130721.jpg"], "Milk from a Feather": [0, "http://www.sputnikmusic.com/images/albums/130735.jpg"], "Equal Phesance": [0, "http://www.sputnikmusic.com/images/albums/130718.jpg"], "Science Everywhere": [0, "http://www.sputnikmusic.com/images/albums/130726.jpg"], "Nature's Mystic Apparition of Time": [0, "http://www.sputnikmusic.com/images/albums/130727.jpg"], "Crystal Marvelous Fruit": [0, "http://www.sputnikmusic.com/images/albums/130717.jpg"], "Quartz On Wind And Knee": [0, "http://www.sputnikmusic.com/images/albums/130719.jpg"], "Perfuming the Foot of the Door": [0, "http://www.sputnikmusic.com/images/albums/130736.jpg"], "Celestial Rag Rug": [0, "http://www.sputnikmusic.com/images/albums/130731.jpg"], "Used Parts Galaxy": [0, "http://www.sputnikmusic.com/images/albums/130716.jpg"], "Star Dive": [0, "http://www.sputnikmusic.com/images/albums/130734.jpg"], "Pass Hidingly Seek": [0, "http://www.sputnikmusic.com/images/albums/102056.jpg"], "Material in Mind": [0, "http://www.sputnikmusic.com/images/albums/130730.jpg"], "Pisces Muse": [0, "http://www.sputnikmusic.com/images/albums/130728.jpg"], "Wake of the Hoods": [0, "http://www.sputnikmusic.com/images/albums/130715.jpg"], "Equal Phesance (2011)": [0, "http://www.sputnikmusic.com/images/albums/130729.jpg"], "Maps in Exodus": [0, "http://www.sputnikmusic.com/images/albums/130725.jpg"]}], "X (series)": ["http://www.sputnikmusic.com/images/unknown2.jpg", ["Rock"], "None", {"X 2012": [0, "http://www.sputnikmusic.com/images/albums/100511.jpg"], "X 2011": [0, "http://www.sputnikmusic.com/images/albums/100508.jpg"], "X 2010": [0, "http://www.sputnikmusic.com/images/albums/100507.jpg"], "X 2003 (Disc 2)": [0, "http://www.sputnikmusic.com/images/albums/100499.jpg"], "X 2008": [0, "http://www.sputnikmusic.com/images/albums/100503.jpg"], "X 2009": [0, "http://www.sputnikmusic.com/images/albums/100506.jpg"], "X 2008 (New Rock Sampler)": [0, "http://www.sputnikmusic.com/images/albums/100504.jpg"], "X 2003 (Disc 1)": [0, "http://www.sputnikmusic.com/images/albums/100496.jpg"], "X Worship 2006": [0, "http://www.sputnikmusic.com/images/albums/100509.jpg"], "X Worship 2007": [0, "http://www.sputnikmusic.com/images/albums/100510.jpg"], "X 2004": [0, "http://www.sputnikmusic.com/images/albums/100498.jpg"], "X 2005": [0, "http://www.sputnikmusic.com/images/albums/100500.jpg"], "X 2006": [0, "http://www.sputnikmusic.com/images/albums/100501.jpg"], "X 2007": [0, "http://www.sputnikmusic.com/images/albums/100502.jpg"]}], "Xrose": ["http://www.sputnikmusic.com/images/unknown2.jpg", ["Emo"], "None", {"My Fervent Ghost": [0, "http://www.sputnikmusic.com/images/albums/124401.jpg"]}], "XXXY": ["http://www.sputnikmusic.com/images/bands/29655.jpg", ["Electronic", "House", "Garage"], "None", {"You Gotta Do You": [0, "http://www.sputnikmusic.com/images/albums/83167.jpg"], "Every Step Forward": [0, "http://www.sputnikmusic.com/images/albums/103679.jpg"], "Rain": [0, "http://www.sputnikmusic.com/images/albums/119490.jpg"], "Got Me So": [0, "http://www.sputnikmusic.com/images/albums/124376.jpg"], "Everything": [0, "http://www.sputnikmusic.com/images/albums/103682.jpg"], "Reflections": [0, "http://www.sputnikmusic.com/images/albums/103677.jpg"], "Bash": [0, "http://www.sputnikmusic.com/images/albums/103674.jpg"]}], "XII Boar": ["http://www.sputnikmusic.com/images/unknown2.jpg", ["Rock"], "None", {"Beyond the Valley of The Triclops": [0, "http://www.sputnikmusic.com/images/albums/228463.jpg"]}], "Xavier Wulf and Bones": ["http://www.sputnikmusic.com/images/bands/48375.jpg", ["Hip-Hop", "Ambient"], "None", {"Caves": [0, "http://www.sputnikmusic.com/images/albums/149073.jpg"]}], "X-Wild": ["http://www.sputnikmusic.com/images/bands/39512.jpg", ["Metal ", "Heavy Metal"], "None", {"Monster Effect": [0, "http://www.sputnikmusic.com/images/albums/109537.jpg"], "So What!": [0, "http://www.sputnikmusic.com/images/albums/109536.jpg"], "Savageland": [0, "http://www.sputnikmusic.com/images/albums/109538.jpg"]}], "Xaos Oblivion": ["http://www.sputnikmusic.com/images/unknown2.jpg", ["Black Metal", "Doom Metal"], "None", {"Black Mountains Spirits": [0, "http://www.sputnikmusic.com/images/albums/173245.jpg"], "Nature's Ancient Wisdom": [0, "http://www.sputnikmusic.com/images/albums/168968.jpg"]}], "xFAMILYx": ["http://www.sputnikmusic.com/images/unknown2.jpg", ["Hardcore"], "None", {"Straight Edge From Birth": [0, "http://www.sputnikmusic.com/images/albums/92795.jpg"]}], "XISFOREYES": ["http://www.sputnikmusic.com/images/bands/16346.jpg", ["Death Metal", "Hardcore", "Black Metal"], "None", {"Absolute Corporeal Besmirchment": [0, "http://www.sputnikmusic.com/images/albums/44521.jpg"], "Insidious Existentialism": [0, "http://www.sputnikmusic.com/images/albums/150841.jpg"], "The Cassandra Syndrome": [0, "http://www.sputnikmusic.com/images/albums/44520.jpg"]}], "Xylouris White": ["http://www.sputnikmusic.com/images/bands/71127.jpg", [], "None", {"Goats": [0, "http://www.sputnikmusic.com/images/albums/203351.jpg"]}], "X (AU)": ["http://www.sputnikmusic.com/images/unknown2.jpg", ["Punk"], "None", {"X-Aspirations": [0, "http://www.sputnikmusic.com/images/albums/128267.jpg"]}], "X Darawish": ["http://www.sputnikmusic.com/images/bands/31566.jpg", ["Indie Pop"], "None", {}], "Xu and Tim Rowe": ["http://www.sputnikmusic.com/images/unknown2.jpg", ["Minimal", "Drone"], "None", {"Blueshift": [0, "http://www.sputnikmusic.com/images/albums/210938.jpg"]}], "Xela Ozzir": ["http://www.sputnikmusic.com/images/unknown2.jpg", ["Experimental", "Electronic"], "None", {"Miowa": [0, "http://www.sputnikmusic.com/images/albums/218109.jpg"]}], "Xerxes": ["http://www.sputnikmusic.com/images/bands/27262.jpg", ["Hardcore", "Post Hardcore"], "None", {"Twins": [0, "http://www.sputnikmusic.com/images/albums/76316.jpg"], "Would you understand?": [0, "http://www.sputnikmusic.com/images/albums/133003.jpg"], "Collision Blonde": [0, "http://www.sputnikmusic.com/images/albums/168507.jpg"], "Our Home Is A Deathbed": [0, "http://www.sputnikmusic.com/images/albums/94734.jpg"], "Homeward Carries No Direction": [0, "http://www.sputnikmusic.com/images/albums/232760.jpg"]}], "Xenophile": ["http://www.sputnikmusic.com/images/bands/76497.jpg", ["Progressive Metal", "Thrash Metal"], "None", {"Systematic Enslavement": [0, "http://www.sputnikmusic.com/images/albums/217977.jpg"]}], "XYZ (USA)": ["http://www.sputnikmusic.com/images/bands/74041.jpg", ["Rock", "Hard Rock"], "None", {"XYZ": [0, "http://www.sputnikmusic.com/images/albums/211403.jpg"], "Hungry": [0, "http://www.sputnikmusic.com/images/albums/211404.jpg"]}], "X-Ray Spex": ["http://www.sputnikmusic.com/images/bands/323.jpg", ["Punk"], "None", {"Germ Free Adolescents": [0, "http://www.sputnikmusic.com/images/albums/482.jpg"]}], "Xentrix": ["http://www.sputnikmusic.com/images/bands/7067.jpg", ["Thrash Metal"], "None", {"For Whose Advantage?": [0, "http://www.sputnikmusic.com/images/albums/20599.jpg"], "The Order Of Chaos": [0, "http://www.sputnikmusic.com/images/albums/77492.jpg"], "Scourge": [0, "http://www.sputnikmusic.com/images/albums/72105.jpg"], "Kin": [0, "http://www.sputnikmusic.com/images/albums/35183.jpg"], "Dilute to Taste": [0, "http://www.sputnikmusic.com/images/albums/72102.jpg"], "Shattered Existence": [0, "http://www.sputnikmusic.com/images/albums/72103.jpg"], "Ghostbusters": [0, "http://www.sputnikmusic.com/images/albums/77490.jpg"]}], "X-Offender": ["http://www.sputnikmusic.com/images/unknown2.jpg", ["Gothic"], "None", {"Dreaming": [0, "http://www.sputnikmusic.com/images/albums/163196.jpg"]}], "Xanadoo": ["http://www.sputnikmusic.com/images/bands/50909.jpg", ["Thrash Metal"], "None", {"Wired Criminal": [0, "http://www.sputnikmusic.com/images/albums/142703.jpg"]}], "XXYYXX": ["http://www.sputnikmusic.com/images/bands/34932.jpg", ["Electronic", "Downtempo"], "None", {"Mystify": [0, "http://www.sputnikmusic.com/images/albums/154726.jpg"], "Still Sound": [0, "http://www.sputnikmusic.com/images/albums/159843.jpg"], "XXYYXX": [0, "http://www.sputnikmusic.com/images/albums/97421.jpg"], "DOLOR": [0, "http://www.sputnikmusic.com/images/albums/105114.jpg"]}], "Xenofanes": ["http://www.sputnikmusic.com/images/bands/69729.jpg", ["Death Metal", "Thrash Metal", "Black Metal"], "None", {"Pissing in the Holy Grail": [0, "http://www.sputnikmusic.com/images/albums/199344.jpg"]}], "X-Men": ["http://www.sputnikmusic.com/images/unknown2.jpg", ["Hip-Hop"], "None", {"Jeunes, Coupables et Libres": [0, "http://www.sputnikmusic.com/images/albums/106002.jpg"]}], "Xela": ["http://www.sputnikmusic.com/images/unknown2.jpg", ["Ambient", "Drone", "Experimental"], "None", {"Exorcism": [0, "http://www.sputnikmusic.com/images/albums/89786.jpg"], "For Frosty Mornings and Summer Nights": [0, "http://www.sputnikmusic.com/images/albums/100640.jpg"], "Tangled Wool": [0, "http://www.sputnikmusic.com/images/albums/232645.jpg"], "The Dead Sea": [0, "http://www.sputnikmusic.com/images/albums/226510.jpg"], "In Bocca Al Lupo": [0, "http://www.sputnikmusic.com/images/albums/232725.jpg"]}], "XS (MTL)": ["http://www.sputnikmusic.com/images/unknown2.jpg", ["Electronic", "Garage", "Techno"], "None", {"Over": [0, "http://www.sputnikmusic.com/images/albums/156082.jpg"], "Spex": [0, "http://www.sputnikmusic.com/images/albums/155826.jpg"]}], "Xandria": ["http://www.sputnikmusic.com/images/bands/8035.jpg", ["Metal ", "Gothic", "Classical"], "None", {"Ravenheart": [0, "http://www.sputnikmusic.com/images/albums/38508.jpg"], "Neverworld's End": [0, "http://www.sputnikmusic.com/images/albums/94885.jpg"], "India": [0, "http://www.sputnikmusic.com/images/albums/23369.jpg"], "Sacrificium": [0, "http://www.sputnikmusic.com/images/albums/159717.jpg"], "Salome - the Seventh Veil": [0, "http://www.sputnikmusic.com/images/albums/38507.jpg"], "Fire & Ashes": [0, "http://www.sputnikmusic.com/images/albums/216820.jpg"], "Kill the Sun": [0, "http://www.sputnikmusic.com/images/albums/38506.jpg"]}], "Xaxaxa": ["http://www.sputnikmusic.com/images/unknown2.jpg", ["Punk", "Indie Rock"], "None", {}], "XenesthiS": ["http://www.sputnikmusic.com/images/unknown2.jpg", ["Metalcore"], "None", {"Sick of Pitch-Black": [0, "http://www.sputnikmusic.com/images/albums/26238.jpg"]}], "XEX": ["http://www.sputnikmusic.com/images/bands/60373.jpg", ["Thrash Metal", "Power Metal", "Heavy Metal"], "None", {"Triad": [0, "http://www.sputnikmusic.com/images/albums/171143.jpg"], "Vier": [0, "http://www.sputnikmusic.com/images/albums/171139.jpg"], "Anything Goes": [0, "http://www.sputnikmusic.com/images/albums/171140.jpg"], "Not for Resale EP": [0, "http://www.sputnikmusic.com/images/albums/171144.jpg"], "Mixed Signals": [0, "http://www.sputnikmusic.com/images/albums/171141.jpg"]}], "X Factor 1": ["http://www.sputnikmusic.com/images/unknown2.jpg", ["Rock"], "None", {"American Dream": [0, "http://www.sputnikmusic.com/images/albums/123116.jpg"]}], "Xandril": ["http://www.sputnikmusic.com/images/unknown2.jpg", ["Thrash Metal", "Power Metal", "Heavy Metal"], "None", {"Perfect Darkness": [0, "http://www.sputnikmusic.com/images/albums/156868.jpg"], "Rehearsal '85": [0, "http://www.sputnikmusic.com/images/albums/156865.jpg"], "The Vision": [0, "http://www.sputnikmusic.com/images/albums/156867.jpg"], "Rotting Paradise": [0, "http://www.sputnikmusic.com/images/albums/156866.jpg"]}], "Xangadix": ["http://www.sputnikmusic.com/images/unknown2.jpg", [], "None", {}], "Xharathorn": ["http://www.sputnikmusic.com/images/unknown2.jpg", ["Black Metal"], "None", {"Immemorial Atlantic Veneration": [0, "http://www.sputnikmusic.com/images/albums/54851.jpg"]}], "X-Panda": ["http://www.sputnikmusic.com/images/bands/31560.jpg", ["Jazz", "Rock"], "None", {"Flight of Fancy": [0, "http://www.sputnikmusic.com/images/albums/88302.jpg"]}], "Xavier Wulf": ["http://www.sputnikmusic.com/images/bands/42417.jpg", ["Hip-Hop"], "None", {"Shut Up and Listen": [0, "http://www.sputnikmusic.com/images/albums/147214.jpg"], "Project X": [0, "http://www.sputnikmusic.com/images/albums/194867.jpg"], "To Be Continued": [0, "http://www.sputnikmusic.com/images/albums/150294.jpg"], "The Wolf Gang's Rodolphe": [0, "http://www.sputnikmusic.com/images/albums/117648.jpg"], "Blood Shore Season Two": [0, "http://www.sputnikmusic.com/images/albums/175433.jpg"], "Blood Shore Season One": [0, "http://www.sputnikmusic.com/images/albums/163779.jpg"], "The Local Man": [0, "http://www.sputnikmusic.com/images/albums/207661.jpg"], "Damare Shizukani": [0, "http://www.sputnikmusic.com/images/albums/125969.jpg"], "Tundra Boy Season One": [0, "http://www.sputnikmusic.com/images/albums/184539.jpg"], "Rare Wulf": [0, "http://www.sputnikmusic.com/images/albums/152330.jpg"], "Sitting Wulf": [0, "http://www.sputnikmusic.com/images/albums/141113.jpg"]}], "Xasma": ["http://www.sputnikmusic.com/images/unknown2.jpg", [], "None", {}], "Xscape": ["http://www.sputnikmusic.com/images/bands/59422.jpg", ["R&B", "Hip-Hop"], "None", {"Traces of My Lipstick": [0, "http://www.sputnikmusic.com/images/albums/168249.jpg"], "Hummin' Comin' at 'Cha": [0, "http://www.sputnikmusic.com/images/albums/168247.jpg"], "Off the Hook": [0, "http://www.sputnikmusic.com/images/albums/168248.jpg"]}], "X-Ray": ["http://www.sputnikmusic.com/images/bands/44496.jpg", ["Metal ", "Heavy Metal", "Hard Rock"], "None", {"Shout!": [0, "http://www.sputnikmusic.com/images/albums/123485.jpg"], "Maten ~Hard Section~": [0, "http://www.sputnikmusic.com/images/albums/123486.jpg"], "Strike Back": [0, "http://www.sputnikmusic.com/images/albums/123489.jpg"], "Dentou Hakai ~Tradition Breaker~": [0, "http://www.sputnikmusic.com/images/albums/123487.jpg"]}], "Xanctux": ["http://www.sputnikmusic.com/images/unknown2.jpg", ["Ambient"], "None", {"Anathemized": [0, "http://www.sputnikmusic.com/images/albums/210302.jpg"]}], "Xoris Perideraio": ["http://www.sputnikmusic.com/images/unknown2.jpg", ["Post Punk"], "None", {}], "Xeerox": ["http://www.sputnikmusic.com/images/unknown2.jpg", [], "None", {"1979 - 1981 Recuerdo Espectral De Un Viejo Decorad": [0, "http://www.sputnikmusic.com/images/albums/230043.jpg"]}], "Xatatax": ["http://www.sputnikmusic.com/images/bands/73264.jpg", ["Punk", "Doom Metal", "Hardcore"], "None", {"May": [0, "http://www.sputnikmusic.com/images/albums/209279.jpg"]}], "Xothist": ["http://www.sputnikmusic.com/images/unknown2.jpg", ["Black Metal", "Ambient", "Noise Rock"], "None", {"Simulacrum": [0, "http://www.sputnikmusic.com/images/albums/168870.jpg"], "Xothist": [0, "http://www.sputnikmusic.com/images/albums/91087.jpg"]}], "XUL": ["http://www.sputnikmusic.com/images/unknown2.jpg", [], "None", {"Malignance": [0, "http://www.sputnikmusic.com/images/albums/164892.jpg"]}], "Xentrifuge": ["http://www.sputnikmusic.com/images/unknown2.jpg", ["Industrial", "Electronic"], "None", {"Converting Infinity": [0, "http://www.sputnikmusic.com/images/albums/158583.jpg"], "Light Extinguished": [0, "http://www.sputnikmusic.com/images/albums/158582.jpg"]}], "Xavier Leon": ["http://www.sputnikmusic.com/images/unknown2.jpg", ["House", "Garage"], "None", {"I Thought You Knew": [0, "http://www.sputnikmusic.com/images/albums/156094.jpg"]}], "XBXRX": ["http://www.sputnikmusic.com/images/bands/9027.jpg", ["Punk"], "None", {"Sixth in Sixes": [0, "http://www.sputnikmusic.com/images/albums/57584.jpg"], "Sixth In Sixes": [0, "http://www.sputnikmusic.com/images/albums/25859.jpg"], "Wars": [0, "http://www.sputnikmusic.com/images/albums/34275.jpg"]}], "Xardas": ["http://www.sputnikmusic.com/images/unknown2.jpg", ["Black Metal"], "\nGloomy black guitar excursions from Lebanon\n", {"Chapter I": [0, "http://www.sputnikmusic.com/images/albums/43470.jpg"]}], "Xaver Scharwenka": ["http://www.sputnikmusic.com/images/unknown2.jpg", ["Classical"], "None", {}], "X-Cops": ["http://www.sputnikmusic.com/images/bands/53415.jpg", ["Metal ", "Punk", "Thrash Metal"], "None", {"You Have The Right To Remain Silent": [0, "http://www.sputnikmusic.com/images/albums/150528.jpg"]}], "Xenomorph": ["http://www.sputnikmusic.com/images/unknown2.jpg", ["Death Metal"], "None", {"Empyreal Regimes": [0, "http://www.sputnikmusic.com/images/albums/66367.jpg"]}], "Xenobiotic": ["http://www.sputnikmusic.com/images/unknown2.jpg", ["Death Metal", "Metalcore"], "None", {"Ares": [0, "http://www.sputnikmusic.com/images/albums/157490.jpg"], "Wraith": [0, "http://www.sputnikmusic.com/images/albums/157568.jpg"]}], "x-Rx": ["http://www.sputnikmusic.com/images/bands/30810.jpg", ["Industrial"], "None", {"Stage 2": [0, "http://www.sputnikmusic.com/images/albums/86197.jpg"]}], "Xihilisk": ["http://www.sputnikmusic.com/images/bands/11726.jpg", ["Indie Rock", "Electronic"], "None", {"0396": [0, "http://www.sputnikmusic.com/images/albums/34815.jpg"], "anEP": [0, "http://www.sputnikmusic.com/images/albums/33277.jpg"], "The Black Square": [0, "http://www.sputnikmusic.com/images/albums/43473.jpg"], "EPTwo": [0, "http://www.sputnikmusic.com/images/albums/33276.jpg"], "Burn In My Fires": [0, "http://www.sputnikmusic.com/images/albums/33521.jpg"]}], "XP8": ["http://www.sputnikmusic.com/images/bands/16149.jpg", ["Industrial", "Electronic"], "None", {"The Art Of Revenge": [0, "http://www.sputnikmusic.com/images/albums/44074.jpg"], "X: A Decade Of Decadence": [0, "http://www.sputnikmusic.com/images/albums/87440.jpg"], "Burning Down": [0, "http://www.sputnikmusic.com/images/albums/110717.jpg"], "Hrs:Min:Sec": [0, "http://www.sputnikmusic.com/images/albums/44073.jpg"], "Want It": [0, "http://www.sputnikmusic.com/images/albums/52301.jpg"], "Drop the Mask": [0, "http://www.sputnikmusic.com/images/albums/44072.jpg"]}], "X Is Loaded": ["http://www.sputnikmusic.com/images/unknown2.jpg", ["Alternative Rock"], "None", {"Raw Nerve": [0, "http://www.sputnikmusic.com/images/albums/44487.jpg"]}], "Xanithon": ["http://www.sputnikmusic.com/images/unknown2.jpg", ["Metal "], "None", {"Serpent": [0, "http://www.sputnikmusic.com/images/albums/89944.jpg"]}], "XTRMST": ["http://www.sputnikmusic.com/images/bands/55637.jpg", ["Hardcore", "Punk"], "\nA straight edge hardcore band, featuring Davey Havok and Jade Puget of AFI\n", {"XTRMST": [0, "http://www.sputnikmusic.com/images/albums/156832.jpg"]}], "xSPONGEXCOREx": ["http://www.sputnikmusic.com/images/bands/60394.jpg", ["Metalcore", "Hardcore"], "None", {"Bikini Bottom Beatdown": [0, "http://www.sputnikmusic.com/images/albums/185293.jpg"], "How Tough Are Yah?": [0, "http://www.sputnikmusic.com/images/albums/171212.jpg"], "The Panty Raid": [0, "http://www.sputnikmusic.com/images/albums/218885.jpg"], "Don't Mess With TexXxas": [0, "http://www.sputnikmusic.com/images/albums/174436.jpg"], "Bold and Thrash": [0, "http://www.sputnikmusic.com/images/albums/185689.jpg"]}], "Xaoz": ["http://www.sputnikmusic.com/images/bands/67448.jpg", ["Death Metal", "Black Metal"], "None", {"Vexilla Regis (Prodeunt Inferni)": [0, "http://www.sputnikmusic.com/images/albums/192377.jpg"]}], "XI": ["http://www.sputnikmusic.com/images/unknown2.jpg", ["Electronic"], "None", {"The Ghost": [0, "http://www.sputnikmusic.com/images/albums/118463.jpg"]}], "X-Sinner": ["http://www.sputnikmusic.com/images/unknown2.jpg", ["Rock"], "None", {"Peace Treaty": [0, "http://www.sputnikmusic.com/images/albums/98554.jpg"], "World Covered in Blood": [0, "http://www.sputnikmusic.com/images/albums/98555.jpg"], "Get It": [0, "http://www.sputnikmusic.com/images/albums/98553.jpg"]}], "xGUMBYx": ["http://www.sputnikmusic.com/images/unknown2.jpg", ["Metalcore"], "None", {"X SLAUGHTER X": [0, "http://www.sputnikmusic.com/images/albums/66927.jpg"]}], "Xenia": ["http://www.sputnikmusic.com/images/bands/34600.jpg", ["Pop "], "None", {"Sing You Home": [0, "http://www.sputnikmusic.com/images/albums/96458.jpg"], "Trash Of Gold": [0, "http://www.sputnikmusic.com/images/albums/197725.jpg"], "Velvet Apple": [0, "http://www.sputnikmusic.com/images/albums/197726.jpg"]}], "XTC": ["http://www.sputnikmusic.com/images/bands/4440.jpg", ["Pop ", "Post Punk", "Psychedelic"], "None", {"The Big Express": [0, "http://www.sputnikmusic.com/images/albums/28514.jpg"], "Drums And Wires": [0, "http://www.sputnikmusic.com/images/albums/22486.jpg"], "Mummer": [0, "http://www.sputnikmusic.com/images/albums/28513.jpg"], "Fossil Fuel: the XTC Singles Collection 1977-1992": [0, "http://www.sputnikmusic.com/images/albums/17205.jpg"], "Nonsuch": [0, "http://www.sputnikmusic.com/images/albums/28516.jpg"], "Wasp Star (Apple Venus Volume 2)": [0, "http://www.sputnikmusic.com/images/albums/74613.jpg"], "Skylarking": [0, "http://www.sputnikmusic.com/images/albums/14478.jpg"], "Oranges & Lemons": [0, "http://www.sputnikmusic.com/images/albums/22152.jpg"], "English Settlement": [0, "http://www.sputnikmusic.com/images/albums/15377.jpg"], "Black Sea": [0, "http://www.sputnikmusic.com/images/albums/28510.jpg"], "Go 2": [0, "http://www.sputnikmusic.com/images/albums/28512.jpg"], "White music": [0, "http://www.sputnikmusic.com/images/albums/12036.jpg"]}], "XS": ["http://www.sputnikmusic.com/images/bands/20393.jpg", ["Pop "], "None", {"Defropauyua": [0, "http://www.sputnikmusic.com/images/albums/57349.jpg"]}], "XV": ["http://www.sputnikmusic.com/images/bands/20819.jpg", ["Hip-Hop"], "None", {"Zero Heroes": [0, "http://www.sputnikmusic.com/images/albums/74870.jpg"], "Everybody's Nobody": [0, "http://www.sputnikmusic.com/images/albums/58668.jpg"], "Awesome EP!": [0, "http://www.sputnikmusic.com/images/albums/200777.jpg"], "Vizzy Zone": [0, "http://www.sputnikmusic.com/images/albums/200772.jpg"], "Madness Begins": [0, "http://www.sputnikmusic.com/images/albums/193083.jpg"], "Complex": [0, "http://www.sputnikmusic.com/images/albums/58472.jpg"], "Popular Culture": [0, "http://www.sputnikmusic.com/images/albums/104195.jpg"], "30 Minute Layover (The Prelude)": [0, "http://www.sputnikmusic.com/images/albums/200773.jpg"]}], "Xibalba (Mex)": ["http://www.sputnikmusic.com/images/unknown2.jpg", ["Black Metal"], "None", {"Ah dzam poop ek": [0, "http://www.sputnikmusic.com/images/albums/126696.jpg"], "In lucescitae tristis hiei": [0, "http://www.sputnikmusic.com/images/albums/126955.jpg"], "Demo 2010": [0, "http://www.sputnikmusic.com/images/albums/126956.jpg"], "Ancients": [0, "http://www.sputnikmusic.com/images/albums/126957.jpg"]}], "xSTORMTROOPERx": ["http://www.sputnikmusic.com/images/bands/60567.jpg", ["Metalcore"], "None", {"The End Of Apathy": [0, "http://www.sputnikmusic.com/images/albums/171712.jpg"]}], "X-Ray Dog": ["http://www.sputnikmusic.com/images/unknown2.jpg", ["Soundtrack"], "None", {"Bites Barks Growls": [0, "http://www.sputnikmusic.com/images/albums/40643.jpg"], "Alpha Dog": [0, "http://www.sputnikmusic.com/images/albums/40613.jpg"], "Cerberus": [0, "http://www.sputnikmusic.com/images/albums/40615.jpg"], "Canis Maximus": [0, "http://www.sputnikmusic.com/images/albums/46554.jpg"]}], "Xhin": ["http://www.sputnikmusic.com/images/unknown2.jpg", ["Techno", "Electronic", "IDM"], "None", {"Sword": [0, "http://www.sputnikmusic.com/images/albums/87815.jpg"]}], "Xixa": ["http://www.sputnikmusic.com/images/unknown2.jpg", [], "None", {"Bloodline": [0, "http://www.sputnikmusic.com/images/albums/220819.jpg"]}], "Xperiment": ["http://www.sputnikmusic.com/images/unknown2.jpg", ["Industrial"], "None", {"First Headshot": [0, "http://www.sputnikmusic.com/images/albums/111525.jpg"], "Visions of Destruction": [0, "http://www.sputnikmusic.com/images/albums/111526.jpg"]}], "X88B88": ["http://www.sputnikmusic.com/images/unknown2.jpg", [], "None", {"X88B88": [0, "http://www.sputnikmusic.com/images/albums/224161.jpg"]}], "Xipe Totec (Mexico)": ["http://www.sputnikmusic.com/images/unknown2.jpg", ["Death Metal", "Progressive Metal"], "None", {"Miquian": [0, "http://www.sputnikmusic.com/images/albums/226384.jpg"], "In Moyocoyani": [0, "http://www.sputnikmusic.com/images/albums/226383.jpg"], "Eztlacuani": [0, "http://www.sputnikmusic.com/images/albums/226380.jpg"]}], "X-Ecutioners": ["http://www.sputnikmusic.com/images/bands/1962.jpg", ["Hip-Hop"], "None", {"X-Pressions": [0, "http://www.sputnikmusic.com/images/albums/61456.jpg"], "Revolutions": [0, "http://www.sputnikmusic.com/images/albums/31510.jpg"], "Built From Scratch": [0, "http://www.sputnikmusic.com/images/albums/4019.jpg"]}], "XieJia": ["http://www.sputnikmusic.com/images/bands/78254.jpg", ["Death Metal", "Black Metal"], "None", {}], "Xhol Caravan": ["http://www.sputnikmusic.com/images/bands/19927.jpg", ["Jazz", "Psychedelic", "Progressive Rock"], "None", {"Electrip": [0, "http://www.sputnikmusic.com/images/albums/55987.jpg"]}], "XO Skeletons": ["http://www.sputnikmusic.com/images/unknown2.jpg", ["Hardcore", "Electronic"], "None", {"Asthmagasm 7\"": [0, "http://www.sputnikmusic.com/images/albums/49207.jpg"]}], "xFILESx": ["http://www.sputnikmusic.com/images/unknown2.jpg", ["Hardcore"], "None", {"Excruciation": [0, "http://www.sputnikmusic.com/images/albums/14735.jpg"], "Demo": [0, "http://www.sputnikmusic.com/images/albums/209498.jpg"], "Beaten Straight EP": [0, "http://www.sputnikmusic.com/images/albums/209500.jpg"], "NBC Mayhem": [0, "http://www.sputnikmusic.com/images/albums/209501.jpg"], "Excruciation & Discography": [0, "http://www.sputnikmusic.com/images/albums/209499.jpg"]}], "xQz": ["http://www.sputnikmusic.com/images/unknown2.jpg", [], "None", {"Backwards Words": [0, "http://www.sputnikmusic.com/images/albums/169852.jpg"], "Balance": [0, "http://www.sputnikmusic.com/images/albums/169915.jpg"]}], "Xoc": ["http://www.sputnikmusic.com/images/unknown2.jpg", ["Experimental"], "None", {"G2EP": [0, "http://www.sputnikmusic.com/images/albums/183689.jpg"], "SMW": [0, "http://www.sputnikmusic.com/images/albums/183686.jpg"], "The Mouse Madness Project": [0, "http://www.sputnikmusic.com/images/albums/183688.jpg"], "Xoc Plays III": [0, "http://www.sputnikmusic.com/images/albums/183691.jpg"], "Emulator": [0, "http://www.sputnikmusic.com/images/albums/186409.jpg"], "What's Pink and Sucks?": [0, "http://www.sputnikmusic.com/images/albums/183687.jpg"]}], "xKINGx": ["http://www.sputnikmusic.com/images/unknown2.jpg", [], "None", {}], "Xecutioner": ["http://www.sputnikmusic.com/images/unknown2.jpg", ["Death Metal"], "None", {"Demo 1986": [0, "http://www.sputnikmusic.com/images/albums/150843.jpg"]}], "X-Press 2": ["http://www.sputnikmusic.com/images/unknown2.jpg", ["Electronic"], "None", {"Muzikizum": [0, "http://www.sputnikmusic.com/images/albums/101141.jpg"], "Makeshift Feelgood": [0, "http://www.sputnikmusic.com/images/albums/101144.jpg"]}], "xLOOKING FORWARDx": ["http://www.sputnikmusic.com/images/bands/3266.jpg", ["Hardcore"], "None", {"Ahoy Crew Members": [0, "http://www.sputnikmusic.com/images/albums/29608.jpg"], "The Path We Tread": [0, "http://www.sputnikmusic.com/images/albums/8572.jpg"], "What This Means To Me": [0, "http://www.sputnikmusic.com/images/albums/29609.jpg"], "Down With The Ship": [0, "http://www.sputnikmusic.com/images/albums/104397.jpg"]}], "XO": ["http://www.sputnikmusic.com/images/unknown2.jpg", ["Alternative Rock", "Shoegaze", "Dream Pop"], "None", {"Heart": [0, "http://www.sputnikmusic.com/images/albums/146578.jpg"], "Some Day": [0, "http://www.sputnikmusic.com/images/albums/41039.jpg"]}], "X-Divide": ["http://www.sputnikmusic.com/images/bands/17916.jpg", ["Industrial"], "None", {"X": [0, "http://www.sputnikmusic.com/images/albums/48551.jpg"]}], "X-Ray Pop": ["http://www.sputnikmusic.com/images/unknown2.jpg", ["Indie Pop", "Electronic"], "None", {"Alcool": [0, "http://www.sputnikmusic.com/images/albums/136175.jpg"], "D-S": [0, "http://www.sputnikmusic.com/images/albums/136176.jpg"], "L'Eurasienne": [0, "http://www.sputnikmusic.com/images/albums/136174.jpg"]}], "Ximena Sarinana": ["http://www.sputnikmusic.com/images/bands/17949.jpg", ["Indie Pop"], "None", {"Mediocre": [0, "http://www.sputnikmusic.com/images/albums/48679.jpg"]}], "xWitnessx": ["http://www.sputnikmusic.com/images/bands/5249.jpg", ["Hardcore"], "None", {"Break Away": [0, "http://www.sputnikmusic.com/images/albums/15178.jpg"], "The Time Is Now": [0, "http://www.sputnikmusic.com/images/albums/15177.jpg"]}], "Xzibit": ["http://www.sputnikmusic.com/images/bands/2861.jpg", ["Hip-Hop"], "None", {"Weapons Of Mass Destruction": [0, "http://www.sputnikmusic.com/images/albums/46933.jpg"], "Greatest Hits": [0, "http://www.sputnikmusic.com/images/albums/77323.jpg"], "40 Dayz & 40 Nightz": [0, "http://www.sputnikmusic.com/images/albums/42698.jpg"], "Restless": [0, "http://www.sputnikmusic.com/images/albums/13424.jpg"], "At The Speed of Life": [0, "http://www.sputnikmusic.com/images/albums/46932.jpg"], "Full Circle": [0, "http://www.sputnikmusic.com/images/albums/46931.jpg"], "Napalm": [0, "http://www.sputnikmusic.com/images/albums/112038.jpg"]}], "Xyxyxma": ["http://www.sputnikmusic.com/images/unknown2.jpg", ["Industrial", "Electronic", "Black Metal"], "None", {"As The Glass Shatters": [0, "http://www.sputnikmusic.com/images/albums/17975.jpg"]}], "Xanadu (NY)": ["http://www.sputnikmusic.com/images/bands/76167.jpg", [], "None", {"Nemuri No Kuni": [0, "http://www.sputnikmusic.com/images/albums/216991.jpg"], "Xanadu": [0, "http://www.sputnikmusic.com/images/albums/217064.jpg"], "Crooked Beloved": [0, "http://www.sputnikmusic.com/images/albums/223920.jpg"]}], "X_X": ["http://www.sputnikmusic.com/images/unknown2.jpg", ["Punk"], "None", {"X Sticky Fingers X": [0, "http://www.sputnikmusic.com/images/albums/160631.jpg"]}], "XXI": ["http://www.sputnikmusic.com/images/bands/70932.jpg", ["Post Hardcore", "Progressive Rock", "Rock"], "None", {"Inside Out": [0, "http://www.sputnikmusic.com/images/albums/202783.jpg"]}], "Xe-NONE": ["http://www.sputnikmusic.com/images/unknown2.jpg", ["Metal "], "None", {"Dancefloration": [0, "http://www.sputnikmusic.com/images/albums/99562.jpg"]}], "X-Fusion": ["http://www.sputnikmusic.com/images/bands/11283.jpg", ["Industrial"], "None", {"Dial D For Demons": [0, "http://www.sputnikmusic.com/images/albums/60977.jpg"], "Rotten To The Core": [0, "http://www.sputnikmusic.com/images/albums/60974.jpg"], "Beyond The Pale": [0, "http://www.sputnikmusic.com/images/albums/60976.jpg"], "Ultima Ratio": [0, "http://www.sputnikmusic.com/images/albums/60972.jpg"], "What Remains Is Black": [0, "http://www.sputnikmusic.com/images/albums/131876.jpg"], "Demons Of Hate": [0, "http://www.sputnikmusic.com/images/albums/60975.jpg"], "Thorn In My Flesh": [0, "http://www.sputnikmusic.com/images/albums/72493.jpg"]}], "Xutos e Pontapes": ["http://www.sputnikmusic.com/images/bands/36740.jpg", ["Rock"], "None", {"Gritos Mudos": [0, "http://www.sputnikmusic.com/images/albums/166079.jpg"], "Circo de Feras": [0, "http://www.sputnikmusic.com/images/albums/166075.jpg"], "Puro": [0, "http://www.sputnikmusic.com/images/albums/166086.jpg"], "88": [0, "http://www.sputnikmusic.com/images/albums/166078.jpg"], "XIII": [0, "http://www.sputnikmusic.com/images/albums/166083.jpg"], "Vida Malvada": [0, "http://www.sputnikmusic.com/images/albums/102599.jpg"], "Cerco": [0, "http://www.sputnikmusic.com/images/albums/166074.jpg"], "Direito ao Deserto": [0, "http://www.sputnikmusic.com/images/albums/166081.jpg"], "Dados Viciados": [0, "http://www.sputnikmusic.com/images/albums/166082.jpg"]}], "Xenophobic Ejaculation": ["http://www.sputnikmusic.com/images/unknown2.jpg", ["Industrial", "Electronic"], "None", {"Xenophobic Ejaculation": [0, "http://www.sputnikmusic.com/images/albums/151959.jpg"]}], "X-Vision": ["http://www.sputnikmusic.com/images/unknown2.jpg", ["Metal ", "Metalcore"], "None", {"So Close, So Far": [0, "http://www.sputnikmusic.com/images/albums/51371.jpg"]}], "Xysma": ["http://www.sputnikmusic.com/images/bands/34439.jpg", ["Grind", "Death Metal", "Pop "], "None", {"Swarming of the Maggots": [0, "http://www.sputnikmusic.com/images/albums/96058.jpg"], "Above the Mind of Morbidity": [0, "http://www.sputnikmusic.com/images/albums/112841.jpg"], "Yeah": [0, "http://www.sputnikmusic.com/images/albums/167456.jpg"]}], "Xanadu": ["http://www.sputnikmusic.com/images/bands/29806.jpg", ["Progressive Rock"], "None", {"Follow The Instinct": [0, "http://www.sputnikmusic.com/images/albums/171937.jpg"], "The Last Sunrise": [0, "http://www.sputnikmusic.com/images/albums/83570.jpg"]}], "xClearx": ["http://www.sputnikmusic.com/images/unknown2.jpg", [], "None", {"The Sickness Must End": [0, "http://www.sputnikmusic.com/images/albums/147999.jpg"], "Deeper Than Blood": [0, "http://www.sputnikmusic.com/images/albums/147998.jpg"]}], "x-wife": ["http://www.sputnikmusic.com/images/bands/37419.jpg", ["Indie Rock", "Post Punk", "Electronic"], "None", {"Infectious Affectional": [0, "http://www.sputnikmusic.com/images/albums/104582.jpg"], "Are You Ready for the Blackout?": [0, "http://www.sputnikmusic.com/images/albums/104581.jpg"]}], "X-In June": ["http://www.sputnikmusic.com/images/bands/36345.jpg", ["Industrial"], "None", {"Hall Of Truth": [0, "http://www.sputnikmusic.com/images/albums/101552.jpg"]}], "xDEATHSTARx": ["http://www.sputnikmusic.com/images/bands/13172.jpg", ["Metalcore", "Rock", "Hardcore"], "None", {"The Triumph (re-issue)": [0, "http://www.sputnikmusic.com/images/albums/47017.jpg"], "The Triumph": [0, "http://www.sputnikmusic.com/images/albums/47018.jpg"], "We Are The Threat": [0, "http://www.sputnikmusic.com/images/albums/36889.jpg"]}], "X-Caliber": ["http://www.sputnikmusic.com/images/bands/33458.jpg", ["Metal "], "None", {"Warriors of the Night": [0, "http://www.sputnikmusic.com/images/albums/93340.jpg"]}], "Xatar": ["http://www.sputnikmusic.com/images/unknown2.jpg", [], "None", {"Alles Oder Nix": [0, "http://www.sputnikmusic.com/images/albums/205935.jpg"], "Baba Aller Babas": [0, "http://www.sputnikmusic.com/images/albums/205937.jpg"], "Nr 415": [0, "http://www.sputnikmusic.com/images/albums/205936.jpg"]}], "Xploding Plastix": ["http://www.sputnikmusic.com/images/bands/7013.jpg", ["Jazz", "Electronic", "Trip Hop"], "None", {"Amateur Girlfriends": [0, "http://www.sputnikmusic.com/images/albums/193697.jpg"], "Amateur Girlfriends Go Proskirt Agents": [0, "http://www.sputnikmusic.com/images/albums/23336.jpg"], "The Benevolent Volume Lurkings": [0, "http://www.sputnikmusic.com/images/albums/229990.jpg"], "Behind The Eightball": [0, "http://www.sputnikmusic.com/images/albums/85011.jpg"], "The Donca Matic Singalongs": [0, "http://www.sputnikmusic.com/images/albums/35973.jpg"], "Treated Timber Resists Rot": [0, "http://www.sputnikmusic.com/images/albums/84015.jpg"]}], "Xenia Rubinos": ["http://www.sputnikmusic.com/images/unknown2.jpg", ["Pop ", "Soul"], "None", {"Black Terry Cat": [0, "http://www.sputnikmusic.com/images/albums/220167.jpg"], "Magic Trix": [0, "http://www.sputnikmusic.com/images/albums/136131.jpg"]}], "Xeno & Oaklander": ["http://www.sputnikmusic.com/images/unknown2.jpg", [], "None", {}], "Xenolith": ["http://www.sputnikmusic.com/images/bands/14896.jpg", ["Death Metal"], "None", {"Obscure Reflections": [0, "http://www.sputnikmusic.com/images/albums/41080.jpg"]}], "Xaltation": ["http://www.sputnikmusic.com/images/unknown2.jpg", ["Reggae"], "None", {}], "xAFBx": ["http://www.sputnikmusic.com/images/unknown2.jpg", ["Metalcore"], "None", {"My Life, Your End": [0, "http://www.sputnikmusic.com/images/albums/71114.jpg"], "Count Your Lies": [0, "http://www.sputnikmusic.com/images/albums/185884.jpg"]}], "X Ambassadors": ["http://www.sputnikmusic.com/images/bands/67254.jpg", ["Indie Pop", "Pop ", "Pop Rock"], "None", {"The Reason": [0, "http://www.sputnikmusic.com/images/albums/191844.jpg"], "VHS": [0, "http://www.sputnikmusic.com/images/albums/191846.jpg"], "Love Songs Drug Songs": [0, "http://www.sputnikmusic.com/images/albums/191843.jpg"]}], "XX": ["http://www.sputnikmusic.com/images/unknown2.jpg", ["Hip-Hop", "Electronic"], "None", {"Lights (Love Sick)": [0, "http://www.sputnikmusic.com/images/albums/152680.jpg"], "Very Wild Night": [0, "http://www.sputnikmusic.com/images/albums/147885.jpg"]}], "Xerdor": ["http://www.sputnikmusic.com/images/unknown2.jpg", ["Rock"], "None", {"All the Sins": [0, "http://www.sputnikmusic.com/images/albums/3572.jpg"]}], "Xet": ["http://www.sputnikmusic.com/images/unknown2.jpg", ["Hip-Hop", "Experimental", "Sludge Metal"], "None", {"The Hazmat Ordeal": [0, "http://www.sputnikmusic.com/images/albums/174045.jpg"]}], "X-TG": ["http://www.sputnikmusic.com/images/bands/71106.jpg", ["Industrial", "Electronic", "Experimental"], "None", {"Live At Porto Casa Musica, Portugal": [0, "http://www.sputnikmusic.com/images/albums/203287.jpg"]}], "X Japan": ["http://www.sputnikmusic.com/images/bands/1062.jpg", ["Progressive Metal", "Power Metal", "Heavy Metal"], "None", {"Dahlia Tour Final 1996": [0, "http://www.sputnikmusic.com/images/albums/185643.jpg"], "Symphonic Silent Jealousy": [0, "http://www.sputnikmusic.com/images/albums/169328.jpg"], "The Last Live Video": [0, "http://www.sputnikmusic.com/images/albums/185644.jpg"], "Symphonic Blue Blood": [0, "http://www.sputnikmusic.com/images/albums/160564.jpg"], "Art of Life": [0, "http://www.sputnikmusic.com/images/albums/1791.jpg"], "The Last Live": [0, "http://www.sputnikmusic.com/images/albums/122641.jpg"], "Jealousy": [0, "http://www.sputnikmusic.com/images/albums/9925.jpg"], "Vanishing Vision": [0, "http://www.sputnikmusic.com/images/albums/9947.jpg"], "Art of Life Live": [0, "http://www.sputnikmusic.com/images/albums/122646.jpg"], "Live Live Live Extra": [0, "http://www.sputnikmusic.com/images/albums/122644.jpg"], "Best": [0, "http://www.sputnikmusic.com/images/albums/1891.jpg"], "The Last Song": [0, "http://www.sputnikmusic.com/images/albums/9948.jpg"], "Dahlia": [0, "http://www.sputnikmusic.com/images/albums/7671.jpg"], "Live Live Live Tokyo Dome 1993-1996": [0, "http://www.sputnikmusic.com/images/albums/122643.jpg"], "Blue Blood": [0, "http://www.sputnikmusic.com/images/albums/9682.jpg"]}], "Xzibit, B-Real and Demrick (Serial Killers)": ["http://www.sputnikmusic.com/images/unknown2.jpg", [], "None", {"The Murder Show": [0, "http://www.sputnikmusic.com/images/albums/202836.jpg"]}], "XYZZY": ["http://www.sputnikmusic.com/images/bands/75226.jpg", ["Electronic", "IDM", "Ambient"], "None", {"Obelus": [0, "http://www.sputnikmusic.com/images/albums/214687.jpg"]}], "xRepresentx": ["http://www.sputnikmusic.com/images/bands/32675.jpg", ["Hardcore"], "\nA straight-edge hardcore band from Pennsylvania\n", {"True At All Costs": [0, "http://www.sputnikmusic.com/images/albums/91249.jpg"]}], "xRepentancex": ["http://www.sputnikmusic.com/images/bands/66244.jpg", ["Metalcore", "Hardcore"], "None", {"The Sickness of Eden": [0, "http://www.sputnikmusic.com/images/albums/188942.jpg"], "Cleansing": [0, "http://www.sputnikmusic.com/images/albums/218397.jpg"]}]}